req_scanner/__init__.py
req_scanner/cli.py
req_scanner/deps.py
req_scanner/scanner.py
req_scanner-0.2.1.dist-info/licenses/LICENSE
req_scanner-0.2.1.dist-info/METADATA
req_scanner-0.2.1.dist-info/WHEEL
req_scanner-0.2.1.dist-info/entry_points.txt
req_scanner-0.2.1.dist-info/top_level.txt
req_scanner-0.2.1.dist-info/RECORD
