Metadata-Version: 2.4
Name: req-scanner
Version: 0.2.1
Summary: A smart tool to analyze, generate, and check Python project requirements.
Author-email: ARsemi4699 <mohali1381@gmail.com>
License: MIT License
Project-URL: Homepage, https://github.com/Arsemi4699/req-scanner
Project-URL: Bug Tracker, https://github.com/Arsemi4699/req-scanner/issues
Keywords: requirements,pip,dependencies,scanner,cli
Classifier: Programming Language :: Python :: 3
Classifier: License :: OSI Approved :: MIT License
Classifier: Operating System :: OS Independent
Classifier: Topic :: Software Development :: Build Tools
Classifier: Topic :: Utilities
Requires-Python: >=3.8
License-File: LICENSE
Requires-Dist: packaging>=21.0
Dynamic: license-file
